version.py
wine_ctl-2.2.0.data/scripts/wine-ctl
wine_ctl-2.2.0.dist-info/COPYING
wine_ctl-2.2.0.dist-info/METADATA
wine_ctl-2.2.0.dist-info/WHEEL
wine_ctl-2.2.0.dist-info/top_level.txt
wine_ctl-2.2.0.dist-info/RECORD
