Metadata-Version: 2.1
Name: wine-ctl
Version: 2.2.0
Summary: Manage Wine Prefixes
Home-page: https://projects.duckcorp.org/projects/wine-ctl
Author: Marc Dequènes (Duck)
Author-email: Duck@DuckCorp.org
License: GPLv3
Keywords: wine
Platform: UNKNOWN
Classifier: Environment :: Console
Classifier: Development Status :: 5 - Production/Stable
Classifier: Intended Audience :: End Users/Desktop
Classifier: License :: OSI Approved :: GNU General Public License v3 or later (GPLv3+)
Classifier: Operating System :: POSIX :: Linux
Classifier: Programming Language :: Python :: 3 :: Only
Classifier: Operating System :: POSIX :: Linux
Classifier: Natural Language :: English
Requires-Python: >=3.6
License-File: COPYING
Requires-Dist: pyyaml (>=5.3.1)
Requires-Dist: jsonschema (>=3.2.0)
Requires-Dist: argcomplete (>=1.9.2)
